tensorboard/__init__.py
tensorboard/assets.py
tensorboard/auth.py
tensorboard/context.py
tensorboard/data_compat.py
tensorboard/dataclass_compat.py
tensorboard/default.py
tensorboard/errors.py
tensorboard/lazy.py
tensorboard/main.py
tensorboard/main_lib.py
tensorboard/manager.py
tensorboard/notebook.py
tensorboard/plugin_util.py
tensorboard/program.py
tensorboard/version.py
tensorboard/webfiles.zip
tensorboard/_vendor/__init__.py
tensorboard/_vendor/bleach/__init__.py
tensorboard/_vendor/bleach/callbacks.py
tensorboard/_vendor/bleach/encoding.py
tensorboard/_vendor/bleach/linkifier.py
tensorboard/_vendor/bleach/sanitizer.py
tensorboard/_vendor/bleach/utils.py
tensorboard/_vendor/bleach/version.py
tensorboard/_vendor/html5lib/__init__.py
tensorboard/_vendor/html5lib/_ihatexml.py
tensorboard/_vendor/html5lib/_inputstream.py
tensorboard/_vendor/html5lib/_tokenizer.py
tensorboard/_vendor/html5lib/_utils.py
tensorboard/_vendor/html5lib/constants.py
tensorboard/_vendor/html5lib/html5parser.py
tensorboard/_vendor/html5lib/serializer.py
tensorboard/_vendor/html5lib/_trie/__init__.py
tensorboard/_vendor/html5lib/_trie/_base.py
tensorboard/_vendor/html5lib/_trie/py.py
tensorboard/_vendor/html5lib/filters/__init__.py
tensorboard/_vendor/html5lib/filters/alphabeticalattributes.py
tensorboard/_vendor/html5lib/filters/base.py
tensorboard/_vendor/html5lib/filters/inject_meta_charset.py
tensorboard/_vendor/html5lib/filters/lint.py
tensorboard/_vendor/html5lib/filters/optionaltags.py
tensorboard/_vendor/html5lib/filters/sanitizer.py
tensorboard/_vendor/html5lib/filters/whitespace.py
tensorboard/_vendor/html5lib/treeadapters/__init__.py
tensorboard/_vendor/html5lib/treeadapters/genshi.py
tensorboard/_vendor/html5lib/treeadapters/sax.py
tensorboard/_vendor/html5lib/treebuilders/__init__.py
tensorboard/_vendor/html5lib/treebuilders/base.py
tensorboard/_vendor/html5lib/treebuilders/dom.py
tensorboard/_vendor/html5lib/treebuilders/etree.py
tensorboard-2.11.1.dist-info/LICENSE
tensorboard-2.11.1.dist-info/METADATA
tensorboard-2.11.1.dist-info/WHEEL
tensorboard-2.11.1.dist-info/entry_points.txt
tensorboard-2.11.1.dist-info/top_level.txt
tensorboard-2.11.1.dist-info/RECORD
